calusern/__init__.py
calusern/__main__.py
calusern/static/a-propos.html
calusern/static/css/master.css
calusern/templates/base.html
calusern/templates/category.html
calusern/templates/entire_exam.html
calusern/templates/exercice.html
calusern/templates/index.html
calusern/templates/solution.html
calusern/templates/year_index.html
calusern-0.2.5.dist-info/LICENSE
calusern-0.2.5.dist-info/METADATA
calusern-0.2.5.dist-info/WHEEL
calusern-0.2.5.dist-info/top_level.txt
calusern-0.2.5.dist-info/RECORD
