Metadata-Version: 2.1
Name: calusern
Version: 0.2.5
Summary: Transforms https://gitlab.com/cedricvanrompay/annales-brevet-et-bac into https://cedricvanrompay.gitlab.io/annales-brevet-et-bac
Home-page: https://gitlab.com/cedricvanrompay/calusern
Author: Cédric Van Rompay
License: UNKNOWN
Project-URL: Bug Reports, https://gitlab.com/cedricvanrompay/calusern/issues
Keywords: annales brevet bac examens
Platform: UNKNOWN
Classifier: Development Status :: 3 - Alpha
Classifier: Intended Audience :: Education
Classifier: Topic :: Text Processing :: Markup
Classifier: Topic :: Documentation
Classifier: Topic :: Education
Classifier: License :: OSI Approved :: MIT License
Classifier: Programming Language :: Python :: 3
Classifier: Programming Language :: Python :: 3.6
Requires-Python: >=3.6
Requires-Dist: docutils
Requires-Dist: jinja2
Requires-Dist: rst2html5
Requires-Dist: pyyaml
